AUTHORS.md
LICENSE.md
MANIFEST.in
Makefile
README.md
requirements.txt
setup.py
tox.ini
update_index.sh
django_pegasus_cms.egg-info/PKG-INFO
django_pegasus_cms.egg-info/SOURCES.txt
django_pegasus_cms.egg-info/dependency_links.txt
django_pegasus_cms.egg-info/requires.txt
django_pegasus_cms.egg-info/top_level.txt
pegasus/__init__.py
pegasus/cms_toolbar.py
pegasus/models.py
pegasus/sitemaps.py
pegasus/storage.py
pegasus/urls.py
pegasus/utils.py
pegasus/views.py
pegasus/wsgi.py
pegasus/apps/__init__.py
pegasus/apps/authors/__init__.py
pegasus/apps/authors/admin.py
pegasus/apps/authors/cms_app.py
pegasus/apps/authors/models.py
pegasus/apps/authors/urls.py
pegasus/apps/authors/views.py
pegasus/apps/authors/templatetags/__init__.py
pegasus/apps/authors/templatetags/author_tags.py
pegasus/apps/content/__init__.py
pegasus/apps/content/admin.py
pegasus/apps/content/cms_app.py
pegasus/apps/content/cms_toolbar.py
pegasus/apps/content/menu.py
pegasus/apps/content/models.py
pegasus/apps/content/search_indexes.py
pegasus/apps/content/urls.py
pegasus/apps/content/views.py
pegasus/apps/content/templatetags/__init__.py
pegasus/apps/content/templatetags/content_tags.py
pegasus/apps/files/__init__.py
pegasus/apps/files/admin.py
pegasus/apps/files/models.py
pegasus/apps/search/__init__.py
pegasus/apps/search/cms_app.py
pegasus/apps/search/forms.py
pegasus/apps/search/models.py
pegasus/apps/search/utils.py
pegasus/apps/search/views.py
pegasus/apps/search/templatetags/__init__.py
pegasus/apps/search/templatetags/search_tags.py
pegasus/extensions/__init__.py
pegasus/extensions/content_list/__init__.py
pegasus/extensions/content_list/admin.py
pegasus/extensions/content_list/cms_toolbar.py
pegasus/extensions/content_list/models.py
pegasus/extensions/content_list/templatetags/__init__.py
pegasus/extensions/content_list/templatetags/list_tags.py
pegasus/extensions/left_nav/__init__.py
pegasus/extensions/left_nav/admin.py
pegasus/extensions/left_nav/cms_toolbar.py
pegasus/extensions/left_nav/models.py
pegasus/extensions/page_extras/__init__.py
pegasus/extensions/page_extras/admin.py
pegasus/extensions/page_extras/cms_toolbar.py
pegasus/extensions/page_extras/models.py
