Metadata-Version: 1.0
Name: django-pegasus-cms
Version: 0.1.7
Summary: tbdtbd
Home-page: https://github.com/celerityweb/django-pegasus-cms/
Author: Matt Caldwell
Author-email: matt.caldwell@gmail.com
License: MIT - see LICENSE file
Platform: UNKNOWN
